Metadata-Version: 1.0
Name: sufuncs
Version: 1.0.6
Summary: Auxiliary functions and functions with additional statistics
Home-page: UNKNOWN
Author: UNKNOWN
Author-email: arsenniyporoshenco@mail.ru
License: UNKNOWN
Platform: UNKNOWN
